wizardcalls/__init__.py
wizardcalls/__main__.py
wizardcalls/args.py
wizardcalls/cli.py
wizardcalls/colors.py
wizardcalls/core.py
wizardcalls/rsrc/code/solution file/.editorconfig
wizardcalls/rsrc/code/solution file/wizardcalls.sln
wizardcalls/rsrc/code/solution file/proj/wizardcalls.filters
wizardcalls/rsrc/code/solution file/proj/wizardcalls.user
wizardcalls/rsrc/code/solution file/proj/wizardcalls.vcxproj
wizardcalls/rsrc/code/solution file/proj/wizardcalls.vcxproj.filters
wizardcalls/rsrc/code/solution file/proj/wizardcalls.vcxproj.user
wizardcalls/rsrc/code/solution file/src/include/wizardcalls.h
wizardcalls/rsrc/code/solution file/src/source/main.c
wizardcalls/rsrc/code/solution file/src/source/wizardcalls.c
wizardcalls/rsrc/code/solution file/src/source/wizardcalls.global.x64.asm
wizardcalls/rsrc/code/solution file/src/source/wizardcalls.x64.asm
wizardcalls/rsrc/code/templates/Djb2.c
wizardcalls/rsrc/code/templates/Jenkins.c
wizardcalls/rsrc/code/templates/Murmur.c
wizardcalls/rsrc/data/nt_api.json
wizardcalls/rsrc/data/type-conversion.json
wizardcalls-2.1.0.dist-info/METADATA
wizardcalls-2.1.0.dist-info/WHEEL
wizardcalls-2.1.0.dist-info/entry_points.txt
wizardcalls-2.1.0.dist-info/RECORD
