Metadata-Version: 2.4
Name: wizardcalls
Version: 2.1.0
Summary: An indirect syscall code generation utility for C/C++ windows impants
Project-URL: Github, https://github.com/wizardy0ga/wizardcalls
Project-URL: Source, https://github.com/wizardy0ga/wizardcalls/tree/master/src/wizardcalls
Project-URL: Documentation, https://github.com/wizardy0ga/wizardcalls/tree/master/docs/en
Author: wizardy0ga
Requires-Python: >=3.10
